MANIFEST.in
README.md
setup.py
XBVC.egg-info/PKG-INFO
XBVC.egg-info/SOURCES.txt
XBVC.egg-info/dependency_links.txt
XBVC.egg-info/entry_points.txt
XBVC.egg-info/requires.txt
XBVC.egg-info/top_level.txt
src/__init__.py
src/objects.py
src/setup.py
src/xbvcgen.py
src/emitters/EmitterBase.py
src/emitters/__init__.py
src/emitters/_emitter_registry.py
src/emitters/c_emitter.py
src/emitters/emitter_factory.py
src/emitters/py_emitter.py
src/emitters/templates/c_header.jinja2
src/emitters/templates/c_interface.jinja2
src/emitters/templates/cobs.c
src/emitters/templates/cobs.h
src/emitters/templates/cobs.py
src/emitters/templates/py_interface.jinja2