Metadata-Version: 1.1
Name: XBVC
Version: 0.0.1
Summary: eXtensible Bit Vector Communication (protocol)
Home-page: https://github.com/Jeff-Ciesielski/XBVC
Author: Jeff Ciesielski
Author-email: jeffciesielski@gmail.com
License: MIT
Keywords: usart communication microcontroller
Platform: UNKNOWN
Classifier: Development Status :: 3 - Alpha
Classifier: Topic :: Utilities
Classifier: License :: OSI Approved :: MIT License
